raptor_framework/__init__.py
raptor_framework-0.0.1.dist-info/METADATA
raptor_framework-0.0.1.dist-info/WHEEL
raptor_framework-0.0.1.dist-info/top_level.txt
raptor_framework-0.0.1.dist-info/RECORD
