Metadata-Version: 2.1
Name: raptor-framework
Version: 0.0.1
Summary: Raptor Framework
Home-page: https://github.com/IgorDantasID/
Author: Igor Dantas de Aguiar
Author-email: igordantas91@icloud.com
License: MIT
Platform: UNKNOWN
Classifier: Programming Language :: Python :: 3
Classifier: License :: OSI Approved :: MIT License
Classifier: Operating System :: OS Independent
Requires-Python: >=3.7
